yuno_sesr/__init__.py
yuno_sesr/SESR_m5_FP32/saved_model.pb
yuno_sesr/SESR_m5_FP32/test.txt
yuno_sesr/SESR_m5_FP32/variables/variables.data-00000-of-00001
yuno_sesr/SESR_m5_FP32/variables/variables.index
yuno_sesr-0.0.1.dist-info/METADATA
yuno_sesr-0.0.1.dist-info/WHEEL
yuno_sesr-0.0.1.dist-info/top_level.txt
yuno_sesr-0.0.1.dist-info/RECORD
