Metadata-Version: 2.1
Name: yuno-sesr
Version: 0.0.1
Summary: Test upload to pypi
Author: yunotao
License: MIT
